qemb/__init__.py
qemb/_version.py
qemb/cli.py
qemb/cut_cluster.py
qemb/find_dirs.py
qemb/jobs.py
qemb/system_class.py
qemb/tackle_poscar.py
qemb/write_inputs.py
qemb-0.1.6.dist-info/licenses/LICENSE
qemb-0.1.6.dist-info/METADATA
qemb-0.1.6.dist-info/WHEEL
qemb-0.1.6.dist-info/entry_points.txt
qemb-0.1.6.dist-info/top_level.txt
qemb-0.1.6.dist-info/RECORD
